gegravity/BaselineData.py
gegravity/MonteCarloGE.py
gegravity/OneSectorGE.py
gegravity/__init__.py
gegravity-0.3.dist-info/LICENSE
gegravity-0.3.dist-info/METADATA
gegravity-0.3.dist-info/WHEEL
gegravity-0.3.dist-info/top_level.txt
gegravity-0.3.dist-info/RECORD
