Metadata-Version: 2.1
Name: gegravity
Version: 0.3
Summary: General equilibrium (GE) gravity modeling tools for international trade
Home-page: https://github.com/peter-herman/gegravity
Author: Peter R. Herman
Author-email: peter.r.herman+gegravity@gmail.com
Project-URL: Bug Tracker, https://github.com/peter-herman/gegravity/issues
Project-URL: Documentation, https://peter-herman.github.io/gegravity/
Classifier: Programming Language :: Python :: 3
Classifier: License :: OSI Approved :: MIT License
Classifier: Operating System :: OS Independent
Requires-Python: >=3.7
License-File: LICENSE
Requires-Dist: numpy >=1.19.2
Requires-Dist: scipy >=1.5.2
Requires-Dist: pandas >=1.1.2
Requires-Dist: gme >=1.3
